sample_poem/__init__.py
sample_poem-0.1.1.dist-info/METADATA
sample_poem-0.1.1.dist-info/WHEEL
sample_poem-0.1.1.dist-info/entry_points.txt
sample_poem-0.1.1.dist-info/RECORD
