Metadata-Version: 2.3
Name: sample-poem
Version: 0.1.1
Summary: 
Author: Your Name
Author-email: you@example.com
Requires-Python: >=3.13
Classifier: Programming Language :: Python :: 3
Classifier: Programming Language :: Python :: 3.13
Requires-Dist: requests (>=2.32.3,<3.0.0)
Project-URL: Homepage, https://github.com/GaddipatiSriram/sample-poem
Project-URL: Repository, https://github.com/GaddipatiSriram/sample-poem
